sime_library.py
sime_library-1.4.dist-info/METADATA
sime_library-1.4.dist-info/WHEEL
sime_library-1.4.dist-info/top_level.txt
sime_library-1.4.dist-info/RECORD
