Metadata-Version: 2.1
Name: sime-library
Version: 1.4
Summary: Library
Home-page: https://dmitros-organization.gitbook.io/sime_library/
Author: Tudjewuj
Author-email: dmiro306@gmail.com
License: MIT
Platform: UNKNOWN
Classifier: License :: OSI Approved :: MIT License
Classifier: Programming Language :: Python :: 3
Classifier: Programming Language :: Python :: 3.6
Classifier: Programming Language :: Python :: 3.7
Classifier: Programming Language :: Python :: 3.8
Classifier: Programming Language :: Python :: 3.9
Requires-Dist: colorama
Requires-Dist: pyshorteners
